MANIFEST.in
README.md
pyproject.toml
requirements.txt
setup.cfg
setup.py
t_proxy/__init__.py
t_proxy/config.py
t_proxy/exceptions.py
t_proxy/t_proxy.py
t_proxy/bin/__init__.py
t_proxy/bin/foxyproxy.xpi
t_proxy/bin/oxylabs.crx
t_proxy/browser/__init__.py
t_proxy/browser/chrome_proxy.py
t_proxy/browser/firefox_proxy.py
t_proxy/browser/t_proxy_core.py
t_proxy/requests/__init__.py
t_proxy/requests/requests_proxy.py
t_proxy/utils/__init__.py
t_proxy/utils/logger.py
t_proxy_toolkit.egg-info/PKG-INFO
t_proxy_toolkit.egg-info/SOURCES.txt
t_proxy_toolkit.egg-info/dependency_links.txt
t_proxy_toolkit.egg-info/not-zip-safe
t_proxy_toolkit.egg-info/requires.txt
t_proxy_toolkit.egg-info/top_level.txt
tests/test_proxy_chrome.py