Metadata-Version: 2.1
Name: t-proxy-toolkit
Version: 0.2.0
Summary: Wrapper around selenium and requests to make it easier to use proxies.
Home-page: https://www.thoughtful.ai/
Author: Thoughtful
Author-email: support@thoughtful.ai
Keywords: t-proxy-toolkit
Classifier: Intended Audience :: Developers
Classifier: Natural Language :: English
Classifier: Programming Language :: Python :: 3
Classifier: Programming Language :: Python :: 3.9
Requires-Python: >=3.9
Requires-Dist: requests<3.0.0,>=2.31.0
Requires-Dist: retry~=0.9.2
Requires-Dist: rpaframework==29.0.0
Requires-Dist: fake-useragent==2.0.3
